faiss_minio/__init__.py
faiss_minio/faiss_minio.py
faiss_minio_connection-0.0.3.dist-info/METADATA
faiss_minio_connection-0.0.3.dist-info/WHEEL
faiss_minio_connection-0.0.3.dist-info/top_level.txt
faiss_minio_connection-0.0.3.dist-info/RECORD
